flask_multipass/__init__.py
flask_multipass/auth.py
flask_multipass/core.py
flask_multipass/data.py
flask_multipass/exceptions.py
flask_multipass/group.py
flask_multipass/identity.py
flask_multipass/util.py
flask_multipass/providers/__init__.py
flask_multipass/providers/authlib.py
flask_multipass/providers/saml.py
flask_multipass/providers/shibboleth.py
flask_multipass/providers/sqlalchemy.py
flask_multipass/providers/static.py
flask_multipass/providers/ldap/__init__.py
flask_multipass/providers/ldap/exceptions.py
flask_multipass/providers/ldap/globals.py
flask_multipass/providers/ldap/operations.py
flask_multipass/providers/ldap/providers.py
flask_multipass/providers/ldap/util.py
flask_multipass-0.11.1.dist-info/METADATA
flask_multipass-0.11.1.dist-info/WHEEL
flask_multipass-0.11.1.dist-info/entry_points.txt
flask_multipass-0.11.1.dist-info/licenses/LICENSE
flask_multipass-0.11.1.dist-info/RECORD
