Metadata-Version: 2.4
Name: Flask-Multipass
Version: 0.11.1
Summary: A pluggable solution for multi-backend authentication with Flask
Project-URL: GitHub, https://github.com/indico/flask-multipass
Author-email: Indico Team <indico-team@cern.ch>
License-Expression: BSD-3-Clause
License-File: LICENSE
Classifier: Environment :: Web Environment
Classifier: Framework :: Flask
Classifier: License :: OSI Approved :: BSD License
Classifier: Programming Language :: Python :: 3.10
Classifier: Programming Language :: Python :: 3.11
Classifier: Programming Language :: Python :: 3.12
Classifier: Programming Language :: Python :: 3.13
Classifier: Programming Language :: Python :: 3.14
Requires-Python: ~=3.10
Requires-Dist: blinker
Requires-Dist: flask
Provides-Extra: authlib
Requires-Dist: authlib>=0.14.1; extra == 'authlib'
Requires-Dist: requests; extra == 'authlib'
Provides-Extra: dev
Requires-Dist: pytest; extra == 'dev'
Requires-Dist: pytest-cov; extra == 'dev'
Requires-Dist: pytest-mock; extra == 'dev'
Requires-Dist: ruff; extra == 'dev'
Provides-Extra: ldap
Requires-Dist: flask-wtf; extra == 'ldap'
Requires-Dist: python-ldap>=3.3.1; extra == 'ldap'
Provides-Extra: saml
Requires-Dist: python3-saml>=1.10.1; extra == 'saml'
Provides-Extra: sqlalchemy
Requires-Dist: flask-wtf; extra == 'sqlalchemy'
Requires-Dist: sqlalchemy; extra == 'sqlalchemy'
